Workbook

Sheet Process Flow Register
A1: PF-ID | B1: Process Flow Name | C1: Category | D1: SOW Module(s) | E1: SOW Req Ref(s) | F1: RIBA Stage(s) | G1: Primary Actor(s) | H1: Key Decision Points | I1: Freeze Interaction | J1: ERP Sync Required | K1: Phase | L1: Priority | M1: Est. Steps | N1: Predecessor PF(s) | O1: Downstream PF(s) | P1: Workshop Ref | Q1: Status | R1: Owner | S1: Notes / Scope Boundary
A2: PF-01 | B2: Document Review | C2: Document Management | D2: M1: EDMS, M2: Doc Workflow | E2: D.1–D.9, SG.1 | F2: 0–8 (All) | G2: Contractor DC, HAI-DC, HAI Engineer, HAI PM | H2: QC Pass/Fail (×2), Review Status (APP/REJ/APP-COM/INFO), Consolidation Validation | I2: Regulatory Freeze blocks design resubmission | J2: No | K2: Ph1 | L2: Critical | M2: 8 | N2: — | O2: PF-03, PF-05, PF-07 | P2: W2, W10 | Q2: To Be Developed | R2: HAI PMO | S2: Full 8-step closed-loop per SOW §4. Includes cover page validation, auto-numbering, SLA timers D+3/D+5/D+7, PDF markup, transmittal register.
A3: PF-02 | B3: Correspondence | C3: Document Management | D3: M3: Correspondence | E3: C.1, C.2 | F3: 4–6 (Execution–Handover) | G3: HAI PM, Contractor, Consultant | H3: Notice validity check, Response deadline, Determination trigger | I3: None direct; supports claims defense | J3: No | K3: Ph1 | L3: Critical | M3: 6 | N3: PF-01 | O3: PF-03, PF-11 | P3: W2 | Q3: To Be Developed | R3: HAI PMO | S3: Letter registry, HAI templates, FIDIC Notice→Response→Determination sequence, email capture, linked to project/contract.
A4: PF-03 | B4: Variation Order | C4: Financial Control | D4: M7: Quality & Site, M15: ERP | E4: G.6, E.1, K.3 | F4: 5 (Construction) | G4: Contractor, HAI QS, HAI PM, HAI Finance, Approver | H4: QS verification, PM endorsement, Finance review, Spatial Coordination breach check, Final approval | I4: Budget Freeze: IPC cannot exceed frozen baseline without variation | J4: Yes — push to ERP for payment | K4: Ph1 | L4: Critical | M4: 6 | N4: PF-01, PF-09 | O4: PF-15 | P4: W3 | Q4: To Be Developed | R4: HAI PMO | S4: Per SOW Roadmap PF-02. BOQ pull, retention calc, advance recovery, threshold flags, KPI: processing time.
A5: PF-04 | B5: Procurement | C5: Financial Control | D5: M7: Execution, M4: Governance | E5: G.1–G.4, G.6, SG.6 | F5: 3–5 (Technical Design–Construction) | G5: PM/Contractor (originator), HAI PM, HAI QS, HAI Finance, Approval Authority | H5: Validity check, Freeze check (triggers PF-06 if frozen), Pricing assessment, Spatial Coordination impact, Value-based delegation | I5: Scope/Technical Design/Budget Freeze: variation on frozen scope triggers PF-06 | J5: Yes — budget baseline update to ERP | K5: Ph1 | L5: Critical | M5: 6 | N5: PF-06, PF-01 | O5: PF-03, PF-15 | P5: W4 | Q5: To Be Developed | R5: HAI PMO | S5: Per SOW Roadmap PF-03. Variation register, contract value adjustment, ERP commitment update, KPI: variation % trend.
A6: PF-05 | B6: Stage Gate | C6: Financial Control | D6: M4: Governance, M15: ERP | E6: G.1, G.5, G.6, E.2 | F6: 0–2 (Pre-Freeze) | G6: HAI PM, HAI Finance, CEO/Management | H6: Spatial Coordination envelope approval, Cost plan level sign-off (L0→L4), Spatial Coordination freeze activation | I6: This flow ACTIVATES Budget Freeze at Gate 3 | J6: Yes — budget baseline lock to ERP | K6: Ph1 | L6: Critical | M6: 5 | N6: PF-08 | O6: PF-04, PF-06, PF-09 | P6: W6, W9 | Q6: To Be Developed | R6: HAI PMO | S6: Covers budget approval at each stage gate. Distinct from variation (PF-04) which modifies post-freeze baseline.
A7: PF-06 | B7: Freeze Exception | C7: Governance Control | D7: M4: Governance Gateways | E7: G.1–G.4, SG.6, SG.7 | F7: 3–6 (Post-Freeze stages) | G7: Requester, HAI PM, HAI Finance, Employer/Senior Authority | H7: Freeze type identification, Technical assessment, Financial impact, Higher-authority approval, Scope-limited lift | I7: Core freeze mechanism — controls all 4 freeze types (Spatial Coordination/Technical Design/Scope/Regulatory) | J7: Yes — if budget freeze exception | K7: Ph1 | L7: Critical | M7: 5 | N7: PF-05, PF-08 | O7: PF-04, PF-09 | P7: W7 | Q7: To Be Developed | R7: HAI PMO | S7: Per SOW Roadmap PF-06. Per-item exception only, not blanket. Freeze reinstated after incorporation. Audit trail mandatory.
A8: PF-07 | B8: Authority Submissions | C8: Procurement | D8: M6: Procurement | E8: P.1–P.3, G.6 | F8: 4 (Tender/RFP) | G8: HAI PM, HAI Procurement, HAI Contracts, Approval Authority | H8: RFP preparation, Bid compliance check, Comparison sheet, Recommendation, Value-based approval, Contract/Contract generation | I8: Budget Freeze must be passed (Gate 3) before procurement module unlocks | J8: Yes — Contract/PO push to ERP | K8: Ph2 | L8: High | M8: 8 | N8: PF-05, PF-06, PF-08 | O8: PF-03, PF-15 | P8: W5 | Q8: To Be Developed | R8: HAI PMO | S8: Per SOW Roadmap PF-04. Supplier database, weighted scoring, template-based Contract/contract generation, ERP PO creation.
A9: PF-08 | B9: IPC Processing | C9: Governance Control | D9: M4: Governance Gateways | E9: SG.1–SG.7, G.5, G.10 | F9: 0–8 (All stages) | G9: HAI PM, Gate Approver(s), System | H9: Exit checklist validation (all items), Gate approval routing, Freeze activation, Next-stage entry verification | I9: Activates applicable freeze rules per stage (Technical Design @ Stg2, Scope/Spatial Coordination @ Stg3, Regulatory @ Stg3.1, All @ Stg4) | J9: No direct; triggers ERP locks via PF-05/PF-06 | K9: Ph1 | L9: Critical | M9: 4 | N9: PF-01, PF-09, PF-11 | O9: PF-05, PF-06, PF-07 | P9: W6 | Q9: To Be Developed | R9: HAI PMO | S9: Per SOW Roadmap PF-05. Master governance flow. 10 gates (0,1,2,3,3.1,4,5,6,7,8). RIBA/RICS/Qatar/GSAS checklist per gate.
A10: PF-09 | B10: Approval Engine | C10: Governance Control | D10: M5: Approval Matrix | E10: G.5–G.9 | F10: 0–8 (All stages) | G10: Requester, System (auto-route), Approver, Delegate | H10: Workflow type identification (7 types), Value threshold check, Delegation check, SLA timer start | I10: Freeze state affects which approval authority is required (higher for exceptions) | J10: No | K10: Ph1 | L10: Critical | M10: 5 | N10: — | O10: PF-03, PF-04, PF-05, PF-07, PF-08 | P10: W9 | Q10: To Be Developed | R10: HAI PMO | S10: 7 workflow types: Spatial Coordination, Comparison, Contract, Advance, IPC, Variation, Technical Design/Gateway. Single approver logic. SLA + escalation.
A11: PF-10 | B11: Quality Supervision | C11: Authority & Compliance | D11: M8: Authority Coordination | E11: A.1, SG.4 | F11: 2–6 (Schematic→BCC) | G11: HAI Technical Design Mgr, HAI PM, System | H11: Package completeness check, Submission authorization, Response tracking, Condition clearance, Gate checklist auto-update | I11: Authority approval feeds stage gate exit criteria; Regulatory Freeze activated at Stage 3.1 | J11: No | K11: Ph2 | L11: High | M11: 6 | N11: PF-01, PF-08 | O11: PF-08 | P11: W8 | Q11: To Be Developed | R11: HAI PMO | S11: Per SOW Roadmap PF-07. QCDD/Kahramaa/Ashghal/Civil Defense. Status board, SLA tracking, condition action items.
A12: PF-11 | B12: Spatial Coordination Cost | C12: Authority & Compliance | D12: M4: Governance, M8: Authority | E12: SG.5 | F12: 0–7 (Registration→Operations) | G12: HAI Technical Design Mgr, HAI PM, GSAS Trust (external) | H12: Registration, Technical Design Assessment (Part 1 & 2), LoC application, Construction audit, Final certificate | I12: GSAS milestones are stage gate exit criteria; no freeze interaction | J12: No | K12: Ph2 | L12: High | M12: 5 | N12: PF-08, PF-10 | O12: PF-08 | P12: W6, W8 | Q12: To Be Developed | R12: HAI PMO | S12: Tracks GSAS lifecycle: registration→concept→design→LoC→construction audit→final cert→operations. Feeds gate checklists.
A13: PF-12 | B13: Risk Register | C13: Quality & Site | D13: M7: Quality & Site | E13: Q.1 | F13: 5 (Construction) | G13: Contractor, HAI QA/QC Engineer, HAI PM | H13: IR submission, Inspection pass/fail, NCR issuance (if fail), Corrective action, Re-inspection, Closure | I13: None direct; NCR closure feeds stage gate exit criteria | J13: No | K13: Ph2 | L13: Critical | M13: 7 | N13: PF-01 | O13: PF-08, PF-14 | P13: W11 | Q13: To Be Developed | R13: HAI PMO | S13: Mandatory fields, linked to project/trade/location. NCR tracks: root cause, corrective action, re-inspection, close-out.
... A24: PF-23 | B24: Predictive Analytics | C24: Predictive Analytics | D24: M14: Analytics | E24: K.8 | F24: 0–8 (Continuous) | G24: System (ML/rule-based), HAI PM | H24: Anomaly detection (bypass, unsigned deliverable, SLA breach pattern), Flag, Investigation trigger | I24: Detects potential freeze violations or gate bypass attempts | J24: No | K24: Ph4 | L24: High | M24: 4 | N24: PF-08, PF-09, PF-17 | O24: PF-06 | P24: — | Q24: To Be Developed | R24: HAI PMO | S24: Bypass flagging, unsigned deliverables, SLA breach patterns, approval timing anomalies. Phase 4 advanced analytics.
A25: PF-24 | B25: Post Go Live Support | C25: Mobilization | D25: MOD023 | E25: Mobilization clause | F25: Stage 0-1 | G25: Contractor, Consultant PM, Resident Engineer, Site Engineers, Safety Officer | H25: Approval of mobilization plan, site setup adequacy, temporary works approval | I25: Technical Design freeze before site establishment | J25: Procurement, Resource Mgmt | K25: Mobilization | L25: High | M25: 12-15 | N25: PF-01 | O25: PF-02, PF-03 | P25: Workshop Phase 1 | Q25: Active | R25: Resident Engineer | S25: Starts with contract execution; ends with substantial mobilization completion
A26: PF-25 | B26: Consultant Mobilisation | C26: Testing & Compliance | D26: MOD024 | E26: T&C and GSAS clause | F26: Stage 6-7 | G26: QA/QC Manager, Authority Representatives, Technical Design Manager, Contractor, Engineer (HAI) | H26: System acceptance, GSAS requirements compliance, authority inspection results, certificate issuance | I26: Technical Design freeze before T&C phase | J26: Quality Management, Compliance | K26: Completion | L26: Critical | M26: 18-22 | N26: PF-20, PF-21 | O26: PF-26 | P26: Workshop Phase 3 | Q26: Active | R26: QA/QC Manager | S26: Starts 4 weeks before practical completion; ends with all certificates and GSAS certification
A27: PF-26 | B27: Final Account Settlement | C27: Handover | D27: MOD025 | E27: Post-occupancy clause | F27: Stage 7-8 | G27: Facility Manager, Resident Engineer, QA/QC Manager, Contractor, End-Users | H27: Complaint categorization, warranty claim acceptance, snagging resolution, FM handover approval | I27: DLP period baseline setting | J27: Facility Mgmt, Asset Mgmt | K27: DLP & Handover | L27: High | M27: 14-18 | N27: PF-25 | O27: PF-23 | P27: Workshop Phase 3 | Q27: Active | R27: Facility Manager | S27: Starts at practical completion; extends through [365 CD] DLP and post-occupancy period
A28: PF-27 | B28: Lessons Learned CI | C28: Payment & Performance | D28: MOD026 | E28: Consultant payment clause | F28: All stages | G28: Consultant PM, Consultant Staff, Finance, Consultant Approval Authority, QS/Cost Manager | H28: Timesheet approval, KPI score verification, deduction justification, payment release authorization | I28: Monthly financial close | J28: AP, Payroll, Performance Mgmt | K28: All phases | L28: High | M28: 10-12 | N28: PF-05 | O28: PF-11 | P28: Workshop Phase 2 | Q28: Active | R28: Consultant PM | S28: Starts with each monthly billing cycle; ends with payment posting to GL
A29: PF-28 | B29: TOC Management | C29: Handover | D29: Handover Management | E29: 6 | F29: High | G29: Construction | H29: Manage the complete TOC process from pre-inspection through certificate issuance per FIDIC SC 10.1 | I29: Engineer (HAI), Contractor, Employer, QA/QC Manager, Resident Engineer | J29: 8 | K29: Application completeness, Inspection readiness, Substantial completion determination, Certificate issuance | L29: TOC issuance time, Defect rate on inspection, Certificate cycle time
A30: PF-29 | B30: Final Payment Certificate | C30: Cost | D30: Cost Management | E30: 7 | F30: High | G30: Construction | H30: Manage the final account settlement process from draft final statement through final payment certificate per FIDIC SC 14.11-14.13 | I30: Contractor, QS/Cost Manager, Engineer (HAI), Employer | J30: 8 | K30: Final account review, Contract value determination, Final payment certification | L30: Final account processing time, Payment cycle time, Claim resolution rate
A31: PF-30 | B31: Performance Certificate | C31: Handover | D31: Handover Management | E31: 7-8 | F31: High | G31: Construction | H31: Manage issuance of Performance Certificate upon completion of DLP obligations per FIDIC SC 11.9 | I31: Engineer (HAI), Contractor, QA/QC Manager, Resident Engineer | J31: 7 | K31: DLP expiry verification, Defect completion status, Performance certificate issuance | L31: PC issuance time, DLP defect closure rate, Certificate cycle time
A32: PF-31 | B32: Snag List Resolution | C32: Quality | D32: Quality Management | E32: 5-7 | F32: Medium | G32: Both | H32: Systematic creation, tracking, and resolution of construction defects/snags throughout project lifecycle | I32: QA/QC Manager, Site Engineers, Contractor, Resident Engineer, Consultant PM | J32: 8 | K32: Snag severity classification, Rectification plan approval, Re-inspection acceptance | L32: Snag creation rate, Closure rate, Average resolution time, Cost of snags
A33: PF-24 | B33: Post Go Live Support | Q33: Issued
A34: PF-25 | B34: Consultant Mobilisation | Q34: Issued
A35: PF-26 | B35: Final Account Settlement | Q35: Issued
A36: PF-27 | B36: Lessons Learned CI | Q36: Issued
A37: PF-28 | B37: TOC Management | Q37: Issued
A38: PF-29 | B38: Final Payment Certificate | Q38: Issued
A39: PF-30 | B39: Performance Certificate | Q39: Issued
A40: PF-31 | B40: Snag List Resolution | Q40: Issued

Sheet Summary
A1: Metric | B1: Value
A2: Total Process Flows | B2: =COUNTA('Process Flow Register'!A2:A100)
A4: ── BY PHASE ──
A5: Phase 1 (Foundation) | B5: =COUNTIF('Process Flow Register'!K2:K100,"Ph1")
A6: Phase 2 (Pilot + Ops) | B6: =COUNTIF('Process Flow Register'!K2:K100,"Ph2")
A7: Phase 3 (ERP + Rollout) | B7: =COUNTIF('Process Flow Register'!K2:K100,"Ph3")
A8: Phase 4 (Analytics) | B8: =COUNTIF('Process Flow Register'!K2:K100,"Ph4")
A10: ── BY PRIORITY ──
A11: Critical | B11: =COUNTIF('Process Flow Register'!L2:L100,"Critical")
A12: High | B12: =COUNTIF('Process Flow Register'!L2:L100,"High")
A13: Medium | B13: =COUNTIF('Process Flow Register'!L2:L100,"Medium")
A15: ── BY CATEGORY ──
A16: Document Management | B16: =COUNTIF('Process Flow Register'!C2:C100,"Document Management")
A17: Financial Control | B17: =COUNTIF('Process Flow Register'!C2:C100,"Financial Control")
A18: Procurement | B18: =COUNTIF('Process Flow Register'!C2:C100,"Procurement")
A19: Governance Control | B19: =COUNTIF('Process Flow Register'!C2:C100,"Governance Control")
A20: Authority & Compliance | B20: =COUNTIF('Process Flow Register'!C2:C100,"Authority & Compliance")
A21: Quality & Site | B21: =COUNTIF('Process Flow Register'!C2:C100,"Quality & Site")
A22: Handover & DLP | B22: =COUNTIF('Process Flow Register'!C2:C100,"Handover & DLP")
A23: KPI & Analytics | B23: =COUNTIF('Process Flow Register'!C2:C100,"KPI & Analytics")
A24: Integration & Access | B24: =COUNTIF('Process Flow Register'!C2:C100,"Integration & Access")
A25: Predictive Analytics | B25: =COUNTIF('Process Flow Register'!C2:C100,"Predictive Analytics")
A27: ── ERP INTEGRATION ──
A28: Flows requiring ERP sync | B28: =COUNTIF('Process Flow Register'!J2:J100,"Yes*")
A29: Flows without ERP sync | B29: =COUNTIF('Process Flow Register'!J2:J100,"No")
A31: ── ESTIMATED TOTAL STEPS ──
A32: Total process steps (all flows) | B32: =SUM('Process Flow Register'!M2:M100)
A34: ── SOW TRACEABILITY ──
A35: Total SOW Requirements covered | B35: 60
A36: Stage Gate requirements (SG.1–SG.7) | B36: 7
A37: EDMS & Workflow requirements (D.1–D.9) | B37: 9
A38: Governance & Approval requirements (G.1–G.10) | B38: 10
A39: Correspondence/Procurement/Quality (C, P, Q) | B39: 8
A40: KPI & Analytics (K.1–K.8) | B40: 8
A41: ERP & Access (E.1–E.4) | B41: 4
A42: Handover & DLP (H.1–H.3) | B42: 3
A43: Authority (A.1) | B43: 1

Sheet SOW Traceability
A1: SOW Ref | B1: Requirement Description | C1: Module | D1: Mapped PF-ID(s) | E1: Phase | F1: Coverage Status
A2: SG.1 | B2: RIBA-aligned entry/exit criteria per stage | C2: Gate | D2: PF-08 | E2: Ph1 | F2: Covered
A3: SG.2 | B3: Stage-gate progression blocking | C3: Gate | D3: PF-08 | E3: Ph1 | F3: Covered
A4: SG.3 | B4: RICS Cost Plan checkpoints per stage | C4: Gate | D4: PF-05, PF-08 | E4: Ph1 | F4: Covered
A5: SG.4 | B5: Qatar authority gate tracking | C5: Gate | D5: PF-10 | E5: Ph1 | F5: Covered
A6: SG.5 | B6: GSAS checkpoint integration | C6: Gate | D6: PF-11 | E6: Ph2 | F6: Covered
A7: SG.6 | B7: Freeze enforcement (Spatial Coordination/Technical Design/Scope/Regulatory) | C7: Gate | D7: PF-06, PF-08 | E7: Ph1 | F7: Covered
A8: SG.7 | B8: Gate exception workflow | C8: Gate | D8: PF-06 | E8: Ph1 | F8: Covered
A9: D.1 | B9: Structured repository by project/discipline/type | C9: EDMS | D9: PF-01 | E9: Ph1 | F9: Covered
A10: D.2 | B10: Automated version control | C10: EDMS | D10: PF-01 | E10: Ph1 | F10: Covered
A11: D.3 | B11: Automated document numbering (HAI convention) | C11: EDMS | D11: PF-01 | E11: Ph1 | F11: Covered
A12: D.4 | B12: Cover page validation | C12: EDMS | D12: PF-01 | E12: Ph1 | F12: Covered
... A51: E.4 | B51: Meeting/calendar + Outlook | C51: Calendar | D51: — | E51: Ph3 | F51: Not Mapped

Sheet Dependency Map
A1: PF-ID | B1: Process Flow Name | C1: Predecessor PF(s) | D1: Downstream PF(s) | E1: Phase | F1: Critical Path?
A2: PF-01 | B2: Document Submission & Review (8-Step Cycle) | C2: — | D2: PF-03, PF-05, PF-07 | E2: Ph1 | F2: YES
A3: PF-02 | B3: Correspondence Management (FIDIC Sequence) | C3: PF-01 | D3: PF-03, PF-11 | E3: Ph1 | F3: No
A4: PF-03 | B4: IPC Certification & Payment | C4: PF-01, PF-09 | D4: PF-15 | E4: Ph1 | F4: No
A5: PF-04 | B5: Variation / Change Order Approval | C5: PF-06, PF-01 | D5: PF-03, PF-15 | E5: Ph1 | F5: No
A6: PF-05 | B6: Spatial Coordination Approval Workflow | C6: PF-08 | D6: PF-04, PF-06, PF-09 | E6: Ph1 | F6: YES
A7: PF-06 | B7: Freeze Exception Workflow | C7: PF-05, PF-08 | D7: PF-04, PF-09 | E7: Ph1 | F7: YES
A8: PF-07 | B8: Procurement (RFP to Contract Award/Contract) | C8: PF-05, PF-06, PF-08 | D8: PF-03, PF-15 | E8: Ph2 | F8: No
A9: PF-08 | B9: Stage-Gate Progression | C9: PF-01, PF-09, PF-11 | D9: PF-05, PF-06, PF-07 | E9: Ph1 | F9: YES
A10: PF-09 | B10: Approval Matrix Routing | C10: — | D10: PF-03, PF-04, PF-05, PF-07, PF-08 | E10: Ph1 | F10: YES
A11: PF-10 | B11: Authority Submission Tracking (DC1/DC2/BCC/NOC) | C11: PF-01, PF-08 | D11: PF-08 | E11: Ph2 | F11: No
A12: PF-11 | B12: GSAS Sustainability Checkpoint Tracking | C12: PF-08, PF-10 | D12: PF-08 | E12: Ph2 | F12: No
... A24: PF-23 | B24: Compliance Anomaly Detection | C24: PF-08, PF-09, PF-17 | D24: PF-06 | E24: Ph4 | F24: No

Sheet Document Control
A1: Document Title | B1: HAI Process Flow Register — Master Inventory
A2: Document Reference | B2: HAI-SS-PFR-2026-001
A3: Version | B3: 1.0 — DRAFT
A4: Date | B4: 27 February 2026
A5: Author | B5: HAI PMO
A6: Classification | B6: Confidential — Internal HAI Working Document
A8: Purpose | B8: Master inventory of all process flows required for SkyStruct Platform customization. Every Level 1–4 deliverable traces back to this register.
A10: Traceability | B10: All 60 SOW requirements (Schedule B) are mapped to at least one process flow. See 'SOW Traceability' sheet for full mapping.
A12: Coverage Gap | B12: E.4 (Meeting/Calendar + Outlook) — not mapped to a process flow. This is a configuration item, not a workflow. Handled in platform setup, not a PF deliverable.
A14: Approval
A15: Prepared by: | B15: [HAI PMO — Name]
A16: Reviewed by: | B16: [HAI Project Director — Name]
A17: Approved by: | B17: [CEO / ED — Name]
A18: Date: | B18: [___________]
